pyprocessmacro/__init__.py
pyprocessmacro/models.py
pyprocessmacro/process.py
pyprocessmacro/utils.py
tests/__init__.py
tests/test_models_accuracy.py
PyProcessMacro-1.0.12.dist-info/LICENSE.txt
PyProcessMacro-1.0.12.dist-info/METADATA
PyProcessMacro-1.0.12.dist-info/WHEEL
PyProcessMacro-1.0.12.dist-info/top_level.txt
PyProcessMacro-1.0.12.dist-info/RECORD
