Metadata-Version: 2.1
Name: PyProcessMacro
Version: 1.0.12
Summary: A Python library for moderation, mediation and conditional process analysis. Based on Andrew F. Hayes Process Macro.
Home-page: https://github.com/QuentinAndre/pyprocessmacro/
Author: Quentin André
Author-email: quentin.andre@insead.edu
License: MIT
Keywords: mediation-analysis,statistics,process,plotting,data-science,data-analysis,data-visualization,regression-models
Platform: UNKNOWN
Classifier: Programming Language :: Python
Classifier: License :: OSI Approved
Classifier: Natural Language :: English
Classifier: Development Status :: 4 - Beta
Classifier: Operating System :: OS Independent
Classifier: Programming Language :: Python :: 3.7
Requires-Python: >=3.7
